Metadata-Version: 2.1
Name: invest_calc
Version: 0.1.0
Summary: Пакет для вычисления ROI и чистой прибыли
Author-email: mikhail <m.zimin@edu.centraluniversity.ru>
Requires-Dist: argparse
